amrlib/__init__.py
amrlib/defaults.py
amrlib/alignments/__init__.py
amrlib/alignments/penman_utils.py
amrlib/alignments/faa_aligner/__init__.py
amrlib/alignments/faa_aligner/faa_aligner.py
amrlib/alignments/faa_aligner/feat2tree.py
amrlib/alignments/faa_aligner/get_alignments.py
amrlib/alignments/faa_aligner/model_aligner_faa.tar.gz
amrlib/alignments/faa_aligner/postprocess.py
amrlib/alignments/faa_aligner/preprocess.py
amrlib/alignments/faa_aligner/proc_data.py
amrlib/alignments/faa_aligner/process_utils.py
amrlib/alignments/faa_aligner/trainer.py
amrlib/alignments/faa_aligner/resources/__init__.py
amrlib/alignments/faa_aligner/resources/amr_id_map.txt
amrlib/alignments/faa_aligner/resources/amr_stopwords.txt
amrlib/alignments/faa_aligner/resources/eng_id_map.txt
amrlib/alignments/faa_aligner/resources/eng_stopwords.txt
amrlib/alignments/faa_aligner/resources/prep-roles_id.txt
amrlib/alignments/isi_hand_alignments/AMR-alignment-format.txt
amrlib/alignments/isi_hand_alignments/README.txt
amrlib/alignments/isi_hand_alignments/__init__.py
amrlib/alignments/isi_hand_alignments/dev-gold.txt
amrlib/alignments/isi_hand_alignments/test-gold.txt
amrlib/alignments/rbw_aligner/__init__.py
amrlib/alignments/rbw_aligner/match_candidates.py
amrlib/alignments/rbw_aligner/rbw_aligner.py
amrlib/alignments/sur_hand_alignments/__init__.py
amrlib/amr_view/Ui_MainWindow.py
amrlib/amr_view/__init__.py
amrlib/amr_view/amr_view.json
amrlib/amr_view/cli.py
amrlib/amr_view/main_window.py
amrlib/amr_view/mainwindow.ui
amrlib/amr_view/processor_gtos.py
amrlib/amr_view/processor_stog.py
amrlib/evaluate/__init__.py
amrlib/evaluate/alignment_scorer.py
amrlib/evaluate/bleu_scorer.py
amrlib/evaluate/smatch_enhanced.py
amrlib/evaluate/smatch_reentracy_srl.py
amrlib/graph_processing/__init__.py
amrlib/graph_processing/amr_loading.py
amrlib/graph_processing/amr_loading_raw.py
amrlib/graph_processing/amr_plot.py
amrlib/graph_processing/annotator.py
amrlib/graph_processing/wiki_adder_blink.py
amrlib-0.8.0.dist-info/LICENSE
amrlib-0.8.0.dist-info/METADATA
amrlib-0.8.0.dist-info/WHEEL
amrlib-0.8.0.dist-info/entry_points.txt
amrlib-0.8.0.dist-info/top_level.txt
amrlib-0.8.0.dist-info/RECORD
