Metadata-Version: 2.1
Name: amrlib
Version: 0.8.0
Summary: A python library that makes AMR parsing, generation and visualization simple.
Home-page: https://github.com/bjascob/amrlib
Author: Brad Jascob
Author-email: bjascob@msn.com
License: UNKNOWN
Platform: UNKNOWN
Classifier: Programming Language :: Python :: 3
Classifier: License :: OSI Approved :: MIT License
Classifier: Operating System :: OS Independent
License-File: LICENSE
Requires-Dist: numpy
Requires-Dist: penman (>=1.1.0)
Requires-Dist: smatch
Requires-Dist: spacy (>=2.0)
Requires-Dist: torch (>=1.6)
Requires-Dist: tqdm
Requires-Dist: transformers (>=4.16)
